odoo/addons/easy_my_coop_easy_migration/README.rst
odoo/addons/easy_my_coop_easy_migration/__init__.py
odoo/addons/easy_my_coop_easy_migration/__manifest__.py
odoo/addons/easy_my_coop_easy_migration/models/__init__.py
odoo/addons/easy_my_coop_easy_migration/models/subscription_request.py
odoo/addons/easy_my_coop_easy_migration/readme/CONTRIBUTORS.rst
odoo/addons/easy_my_coop_easy_migration/readme/DESCRIPTION.rst
odoo/addons/easy_my_coop_easy_migration/readme/INSTALL.rst
odoo/addons/easy_my_coop_easy_migration/readme/ROADMAP.rst
odoo/addons/easy_my_coop_easy_migration/static/description/index.html
odoo12_addon_easy_my_coop_easy_migration-12.0.1.0.0.dist-info/METADATA
odoo12_addon_easy_my_coop_easy_migration-12.0.1.0.0.dist-info/WHEEL
odoo12_addon_easy_my_coop_easy_migration-12.0.1.0.0.dist-info/top_level.txt
odoo12_addon_easy_my_coop_easy_migration-12.0.1.0.0.dist-info/RECORD
